{"format":"norscode-bytecode-v1","entry":"__main__.start","imports":[],"route_handlers":[],"dependency_providers":{},"guard_providers":{},"request_middlewares":[],"response_middlewares":[],"error_middlewares":[],"startup_hooks":[],"shutdown_hooks":[],"tests":[],"functions":{"__main__.hent":{"name":"hent","module":"__main__","params":["nokkel"],"is_async":false,"code":[["LOAD_NAME","nokkel"],["CALL","builtin.miljo_hent",1],["RETURN"]]},"__main__.finnes":{"name":"finnes","module":"__main__","params":["nokkel"],"is_async":false,"code":[["LOAD_NAME","nokkel"],["CALL","builtin.miljo_finnes",1],["RETURN"]]},"__main__.sett":{"name":"sett","module":"__main__","params":["nokkel","verdi"],"is_async":false,"code":[["LOAD_NAME","nokkel"],["LOAD_NAME","verdi"],["CALL","builtin.miljo_sett",2],["RETURN"]]}}}