{"format":"norscode-bytecode-v1","entry":"__main__.start","imports":[],"route_handlers":[],"dependency_providers":{},"guard_providers":{},"request_middlewares":[],"response_middlewares":[],"error_middlewares":[],"startup_hooks":[],"shutdown_hooks":[],"tests":[],"functions":{"__main__.ny":{"name":"ny","module":"__main__","params":["type_navn","melding"],"is_async":false,"code":[["LOAD_NAME","type_navn"],["PUSH_CONST",": "],["BINARY_ADD"],["LOAD_NAME","melding"],["BINARY_ADD"],["RETURN"]]},"__main__.io":{"name":"io","module":"__main__","params":["melding"],"is_async":false,"code":[["PUSH_CONST","IOFeil"],["LOAD_NAME","melding"],["CALL","__main__.ny",2],["RETURN"]]},"__main__.verdi":{"name":"verdi","module":"__main__","params":["melding"],"is_async":false,"code":[["PUSH_CONST","VerdiFeil"],["LOAD_NAME","melding"],["CALL","__main__.ny",2],["RETURN"]]},"__main__.typefeil":{"name":"typefeil","module":"__main__","params":["melding"],"is_async":false,"code":[["PUSH_CONST","TypeFeil"],["LOAD_NAME","melding"],["CALL","__main__.ny",2],["RETURN"]]},"__main__.indeks":{"name":"indeks","module":"__main__","params":["melding"],"is_async":false,"code":[["PUSH_CONST","IndeksFeil"],["LOAD_NAME","melding"],["CALL","__main__.ny",2],["RETURN"]]},"__main__.nøkkel":{"name":"nøkkel","module":"__main__","params":["melding"],"is_async":false,"code":[["PUSH_CONST","NøkkelFeil"],["LOAD_NAME","melding"],["CALL","__main__.ny",2],["RETURN"]]},"__main__.overflyt":{"name":"overflyt","module":"__main__","params":["melding"],"is_async":false,"code":[["PUSH_CONST","OverflytFeil"],["LOAD_NAME","melding"],["CALL","__main__.ny",2],["RETURN"]]},"__main__.tomt":{"name":"tomt","module":"__main__","params":["melding"],"is_async":false,"code":[["PUSH_CONST","TomtFeil"],["LOAD_NAME","melding"],["CALL","__main__.ny",2],["RETURN"]]},"__main__.ikkje_implementert":{"name":"ikkje_implementert","module":"__main__","params":["melding"],"is_async":false,"code":[["PUSH_CONST","IkkjeImplementertFeil"],["LOAD_NAME","melding"],["CALL","__main__.ny",2],["RETURN"]]},"__main__.argument":{"name":"argument","module":"__main__","params":["melding"],"is_async":false,"code":[["PUSH_CONST","ArgumentFeil"],["LOAD_NAME","melding"],["CALL","__main__.ny",2],["RETURN"]]},"__main__.tilstand":{"name":"tilstand","module":"__main__","params":["melding"],"is_async":false,"code":[["PUSH_CONST","TilstandsFeil"],["LOAD_NAME","melding"],["CALL","__main__.ny",2],["RETURN"]]},"__main__.kast_viss_usann":{"name":"kast_viss_usann","module":"__main__","params":["vilkår","melding"],"is_async":false,"code":[["LOAD_NAME","vilkår"],["UNARY_NOT"],["JUMP_IF_FALSE","__L0__"],["PUSH_CONST","AssertFeil: "],["LOAD_NAME","melding"],["BINARY_ADD"],["THROW"],["LABEL","__L0__"],["PUSH_CONST",true],["RETURN"]]},"__main__.kast_viss_tom":{"name":"kast_viss_tom","module":"__main__","params":["tekstverdi","namn"],"is_async":false,"code":[["LOAD_NAME","tekstverdi"],["PUSH_CONST",""],["CALL","builtin.tekst_inneholder",2],["JUMP_IF_FALSE","__L4__"],["LOAD_NAME","tekstverdi"],["CALL","builtin.lengde",1],["PUSH_CONST",0],["COMPARE_EQ"],["JUMP","__L5__"],["LABEL","__L4__"],["PUSH_CONST",false],["LABEL","__L5__"],["JUMP_IF_FALSE","__L2__"],["PUSH_CONST","ArgumentFeil"],["LOAD_NAME","namn"],["PUSH_CONST"," kan ikkje vere tom"],["BINARY_ADD"],["CALL","__main__.ny",2],["THROW"],["LABEL","__L2__"],["LOAD_NAME","tekstverdi"],["RETURN"]]},"__main__.kast_viss_utanfor":{"name":"kast_viss_utanfor","module":"__main__","params":["verdi","min_v","maks_v","namn"],"is_async":false,"code":[["LOAD_NAME","verdi"],["LOAD_NAME","min_v"],["COMPARE_LT"],["JUMP_IF_FALSE","__L8__"],["PUSH_CONST",true],["JUMP","__L9__"],["LABEL","__L8__"],["LOAD_NAME","verdi"],["LOAD_NAME","maks_v"],["COMPARE_GT"],["LABEL","__L9__"],["JUMP_IF_FALSE","__L6__"],["PUSH_CONST","ArgumentFeil"],["LOAD_NAME","namn"],["PUSH_CONST"," må vere mellom "],["BINARY_ADD"],["LOAD_NAME","min_v"],["CALL","builtin.tekst_fra_heltall",1],["BINARY_ADD"],["PUSH_CONST"," og "],["BINARY_ADD"],["LOAD_NAME","maks_v"],["CALL","builtin.tekst_fra_heltall",1],["BINARY_ADD"],["PUSH_CONST",", fekk "],["BINARY_ADD"],["LOAD_NAME","verdi"],["CALL","builtin.tekst_fra_heltall",1],["BINARY_ADD"],["CALL","__main__.ny",2],["THROW"],["LABEL","__L6__"],["LOAD_NAME","verdi"],["RETURN"]]},"__main__.feil_type":{"name":"feil_type","module":"__main__","params":["feiltekst"],"is_async":false,"code":[["LOAD_NAME","feiltekst"],["PUSH_CONST",":"],["CALL","builtin.index_of",2],["STORE_NAME","kolon"],["LOAD_NAME","kolon"],["PUSH_CONST",0],["COMPARE_LT"],["JUMP_IF_FALSE","__L10__"],["LOAD_NAME","feiltekst"],["RETURN"],["LABEL","__L10__"],["LOAD_NAME","feiltekst"],["PUSH_CONST",0],["LOAD_NAME","kolon"],["CALL","builtin.slice",3],["RETURN"]]},"__main__.feil_melding":{"name":"feil_melding","module":"__main__","params":["feiltekst"],"is_async":false,"code":[["LOAD_NAME","feiltekst"],["PUSH_CONST",":"],["CALL","builtin.index_of",2],["STORE_NAME","kolon"],["LOAD_NAME","kolon"],["PUSH_CONST",0],["COMPARE_LT"],["JUMP_IF_FALSE","__L12__"],["LOAD_NAME","feiltekst"],["RETURN"],["LABEL","__L12__"],["LOAD_NAME","feiltekst"],["LOAD_NAME","kolon"],["PUSH_CONST",1],["BINARY_ADD"],["LOAD_NAME","feiltekst"],["CALL","builtin.lengde",1],["CALL","builtin.slice",3],["CALL","builtin.tekst_trim",1],["RETURN"]]}}}